{
  "name": "WebAPI (C# .NET)",
  "steps": [
    {
      "action": "remove",
      "files": ["./assets/DbScripts/SqlServer/2 - FastAPI logs.sql"]
    },
    {
      "action": "replace-text",
      "target": [
        "./assets/DbScripts/SqlServer/1 - Init.sql",
        "./assets/DbScripts/SqlServer/2 - WebAPI logs.sql",
        "./assets/DbScripts/SqlServer/3 - DB User.sql",
        "./src/Scaffold/appsettings.Development.json",
        "./src/ReadMe.md"
      ],
      "match": "Scaff_DB",
      "to": "${dbName}",
      "comment": "Replace 'Scaffold' with namespace in multiple files"
    },
    {
      "action": "replace-text",
      "target": "./spa-src/src/appConfig.ts",
      "match": "User.ReadWrite",
      "to": "User.Read",
      "comment": "Downgrade MS Graph permission"
    },
    {
      "action": "replace-text",
      "target": [
        "./spa-src/.env",
        "./spa-src/src/appConfig.ts",
        "./src/.vscode/launch.json"
      ],
      "match": "5011",
      "to": "${apiPort}",
      "comment": "Set dynamic API port"
    },
    {
      "action": "replace-text",
      "target": [
        "./src/.vscode/launch.json",
        "./src/.vscode/tasks.json",
        "./src/.vscode/settings.json",
        "./spa-src/.vscode/settings.json"
      ],
      "match": "Scaffold",
      "to": "${ns}",
      "comment": "Replace 'Scaffold' with namespace in multiple files"
    },
    {
      "action": "replace-text",
      "target": "./spa-src/package.json",
      "match": "line-of-business",
      "to": "${nslower}",
      "comment": "Replace 'line-of-business' witn namespace in package.json"
    },
    {
      "action": "replace-text",
      "target": "./spa-src/vite.config.ts",
      "match": "3011",
      "to": "${spaPort}",
      "comment": "Replace port in vite.config.ts"
    },
    {
      "action": "replace-text",
      "target": "./spa-src/src/layout/sidebar/index.tsx",
      "match": "Scaff <sup>00</sup>",
      "to": "${title}",
      "comment": "Title on Sidebar"
    },
    {
      "action": "remove-scripts",
      "target": "./spa-src/package.json",
      "scripts": ["build:fastapi"],
      "comment": "Safely remove Python-related npm scripts"
    },
    {
      "action": "replace-text",
      "target": "./spa-src/package.json",
      "match": "build:webapi",
      "to": "build:release",
      "comment": "renaming the build script"
    }
  ]
}
